
<company>
  <employee>
    <id>1</id>
    <fName>John</fName>
    <lName>Doe</lName>
    <address>
      <house>H# 38</house>
      <road>R# 3</road>
      <area>Banani</area>
      <city>Dhaka</city>
    </address>
    <department>Sales</department>
    <salary>$20000</salary>
  </employee>

  <employee>
    <id>2</id>
    <fName>Mark</fName>
    <lName>Zuckerberg</lName>
    <address>
      <flat>Flat# A/1</flat>
      <house>H# 20</house>
      <road>R# 18</road>
      <area>Mirpur</area>
      <city>Dhaka</city>
    </address>
    <department>Accounts</department>
    <salary>$12000</salary>
  </employee>

  <employee>
    <id>3</id>
    <fName>Ala</fName>
    <lName>Voski</lName>
    <address>
      <house>H# 38</house>
      <road>R# 3</road>
      <area>Motijheel</area>
    </address>
    <department>Human Resource</department>
    <salary>$30000</salary>
  </employee>
</company>